<?xml version="1.0"?>
<!DOCTYPE CHARACTERISTIC-LIST [
<!ELEMENT CHARACTERISTIC-LIST (CHARACTERISTIC+)>
<!ELEMENT CHARACTERISTIC (PARM*)>
<!ATTLIST CHARACTERISTIC
	TYPE CDATA #REQUIRED
	VALUE CDATA #IMPLIED
>
<!ELEMENT PARM EMPTY>
<!ATTLIST PARM
	NAME CDATA #REQUIRED
	VALUE CDATA #REQUIRED
>
]>
<CHARACTERISTIC-LIST>
   <CHARACTERISTIC TYPE="ADDRESS">
		<PARM NAME="BEARER" VALUE="GSM/CSD"/>
		<PARM NAME="PROXY" VALUE="195.134.100.01"/>
		<PARM NAME="PORT" VALUE="9203"/>
		<PARM NAME="CSD_DIALSTRING" VALUE="+35833151001"/>
		<PARM NAME="CSD_AUTHTYPE" VALUE="PAP"/>
		<PARM NAME="CSD_AUTHNAME" VALUE="user"/>
		<PARM NAME="CSD_AUTHSECRET" VALUE="secret"/>
		<PARM NAME="CSD_CALLTYPE" VALUE="ANALOGUE"/>
		<PARM NAME="CSD_CALLSPEED" VALUE="AUTO"/>
        <PARM NAME="PROXY_AUTHNAME" VALUE="pxauthname"/>
		<PARM NAME="PROXY_AUTHSECRET" VALUE="pxauthsecret"/>
		<PARM NAME="ISP_NAME" VALUE="World Access ISP"/>
	</CHARACTERISTIC>
	<CHARACTERISTIC TYPE="ADDRESS">
		<PARM NAME="BEARER" VALUE="GSM/SMS"/>
		<PARM NAME="PROXY" VALUE="1065501"/>
		<PARM NAME="SMS_SMSC_ADDRESS" VALUE="+358508771021"/>
	</CHARACTERISTIC>
	<CHARACTERISTIC TYPE="ADDRESS">
		<PARM NAME="BEARER" VALUE="GSM/CSD"/>
		<PARM NAME="PROXY" VALUE="195.134.200.01"/>
		<PARM NAME="PORT" VALUE="9200"/>
		<PARM NAME="CSD_DIALSTRING" VALUE="+35833152001"/>
	</CHARACTERISTIC>
	<CHARACTERISTIC TYPE="ADDRESS">
		<PARM NAME="BEARER" VALUE="GSM/SMS"/>
		<PARM NAME="PROXY" VALUE="1065502"/>
		<PARM NAME="PORT" VALUE="9202"/>
		<PARM NAME="SMS_SMSC_ADDRESS" VALUE="+358508771022"/>
	</CHARACTERISTIC>
	<CHARACTERISTIC TYPE="ADDRESS">
		<PARM NAME="BEARER" VALUE="GSM/CSD"/>
		<PARM NAME="PROXY" VALUE="195.134.300.01"/>
		<PARM NAME="CSD_DIALSTRING" VALUE="+35833153001"/>
        <PARM NAME="CSD_AUTHTYPE" VALUE="PAP"/>
		<PARM NAME="CSD_AUTHNAME" VALUE="user"/>
		<PARM NAME="CSD_AUTHSECRET" VALUE="password"/>
		<PARM NAME="CSD_CALLTYPE" VALUE="ANALOGUE"/>
		<PARM NAME="CSD_CALLSPEED" VALUE="AUTO"/>
	</CHARACTERISTIC>
    	<CHARACTERISTIC TYPE="ADDRESS">
		<PARM NAME="BEARER" VALUE="GSM/SMS"/>
		<PARM NAME="PROXY" VALUE="1065503"/>
		<PARM NAME="PORT" VALUE="9200"/>
		<PARM NAME="SMS_SMSC_ADDRESS" VALUE="+358508771023"/>
	</CHARACTERISTIC>
    	<CHARACTERISTIC TYPE="ADDRESS">
		<PARM NAME="BEARER" VALUE="GSM/CSD"/>
		<PARM NAME="PROXY" VALUE="195.134.400.01"/>
		<PARM NAME="PORT" VALUE="9201"/>
		<PARM NAME="CSD_DIALSTRING" VALUE="+35833154001"/>
		<PARM NAME="CSD_AUTHTYPE" VALUE="CHAP"/>
		<PARM NAME="CSD_AUTHNAME" VALUE="another"/>
		<PARM NAME="CSD_AUTHSECRET" VALUE="shhhhhh"/>
		<PARM NAME="CSD_CALLTYPE" VALUE="ISDN"/>
		<PARM NAME="CSD_CALLSPEED" VALUE="14400"/>
		<PARM NAME="PROXY_AUTHNAME" VALUE="wapuser"/>
		<PARM NAME="PROXY_AUTHSECRET" VALUE="wappswrd"/>
		<PARM NAME="ISP_NAME" VALUE="Another ISP"/>
	</CHARACTERISTIC>
	<CHARACTERISTIC TYPE="ADDRESS">
		<PARM NAME="BEARER" VALUE="GSM/SMS"/>
		<PARM NAME="PROXY" VALUE="1065504"/>
		<PARM NAME="PORT" VALUE="9203"/>
		<PARM NAME="SMS_SMSC_ADDRESS" VALUE="+358508771024"/>
	</CHARACTERISTIC>
	<CHARACTERISTIC TYPE="ADDRESS">
		<PARM NAME="BEARER" VALUE="GSM/CSD"/>
		<PARM NAME="PROXY" VALUE="195.134.500.01"/>
		<PARM NAME="PORT" VALUE="9201"/>
		<PARM NAME="CSD_DIALSTRING" VALUE="+35833155001"/>
		<PARM NAME="CSD_AUTHTYPE" VALUE="PAP"/>
		<PARM NAME="CSD_AUTHNAME" VALUE="tstuser"/>
		<PARM NAME="CSD_AUTHSECRET" VALUE="pw4tstu"/>
		<PARM NAME="CSD_CALLTYPE" VALUE="ANALOGUE"/>
		<PARM NAME="CSD_CALLSPEED" VALUE="28800"/>
		<PARM NAME="PROXY_AUTHNAME" VALUE="wapuser"/>
		<PARM NAME="PROXY_AUTHSECRET" VALUE="wappswrd"/>
		<PARM NAME="ISP_NAME" VALUE="Yet another ISP"/>
	</CHARACTERISTIC>
	<CHARACTERISTIC TYPE="ADDRESS">
		<PARM NAME="BEARER" VALUE="GSM/SMS"/>
		<PARM NAME="PROXY" VALUE="1065505"/>
		<PARM NAME="SMS_SMSC_ADDRESS" VALUE="+358508771025"/>
	</CHARACTERISTIC>
	<CHARACTERISTIC TYPE="ADDRESS">
		<PARM NAME="BEARER" VALUE="GSM/CSD"/>
		<PARM NAME="PROXY" VALUE="195.134.600.01"/>
		<PARM NAME="PORT" VALUE="9201"/>
		<PARM NAME="CSD_DIALSTRING" VALUE="+35833156001"/>
		<PARM NAME="CSD_AUTHTYPE" VALUE="PAP"/>
		<PARM NAME="CSD_AUTHNAME" VALUE="another"/>
		<PARM NAME="CSD_AUTHSECRET" VALUE="shhhhhh"/>
		<PARM NAME="PROXY_AUTHNAME" VALUE="username"/>
		<PARM NAME="PROXY_AUTHSECRET" VALUE="userauthname"/>
		<PARM NAME="CSD_CALLSPEED" VALUE="43200"/>
		<PARM NAME="CSD_CALLTYPE" VALUE="ANALOGUE"/>
	</CHARACTERISTIC>
	<CHARACTERISTIC TYPE="ADDRESS">
		<PARM NAME="BEARER" VALUE="GSM/SMS"/>
		<PARM NAME="PROXY" VALUE="1065506"/>
		<PARM NAME="PORT" VALUE="9203"/>
		<PARM NAME="SMS_SMSC_ADDRESS" VALUE="+358508771026"/>
	</CHARACTERISTIC>
 	<CHARACTERISTIC TYPE="URL" VALUE="/extindex11.wml"/>
	<CHARACTERISTIC TYPE="NAME">
		<PARM NAME="NAME" VALUE="WAP 0023"/>
	</CHARACTERISTIC>
</CHARACTERISTIC-LIST>
